prompt_components/__init__.py
prompt_components/component.py
prompt_components/decorators.py
prompt_components-0.1.1.dist-info/METADATA
prompt_components-0.1.1.dist-info/WHEEL
prompt_components-0.1.1.dist-info/top_level.txt
prompt_components-0.1.1.dist-info/RECORD
