Metadata-Version: 2.4
Name: prompt-components
Version: 0.1.1
Summary: A better library for prompt management.
Requires-Python: >=3.12
Requires-Dist: jinja2>=3.1.6
